build_the_bot/__init__.py
build_the_bot/interaction.py
build_the_bot/state.py
build_the_bot/nlp/__init__.py
build_the_bot/nlp/chat_gpt.py
build_the_bot/nlp/regex.py
build_the_bot/nlp/spacy_training.py
build_the_bot/nlp/spacy_utils.py
build_the_bot-1.0.3.dist-info/licenses/LICENSE
build_the_bot-1.0.3.dist-info/METADATA
build_the_bot-1.0.3.dist-info/WHEEL
build_the_bot-1.0.3.dist-info/top_level.txt
build_the_bot-1.0.3.dist-info/RECORD
