Metadata-Version: 2.4
Name: build_the_bot
Version: 1.0.3
Summary: A chatbot framework
Author-email: Ava Gerami <ava.gerami@viasat.com>
License-Expression: Apache-2.0
Classifier: Programming Language :: Python :: 3
Classifier: Operating System :: OS Independent
Requires-Python: >=3.9.18
License-File: LICENSE
Requires-Dist: aiohttp
Requires-Dist: openai
Requires-Dist: slack_sdk
Requires-Dist: spacy
Provides-Extra: test
Requires-Dist: pytest; extra == "test"
Requires-Dist: pytest-asyncio; extra == "test"
Dynamic: license-file
